Workbook

Sheet Leyenda
A1: CapitalDex — Universo de empresas
A2: Generado el 2026-10-15 desde Yahoo Finance (yfinance). Datos con retraso; solo para diseño del juego.
A4: Celdas editables (texto azul, fondo amarillo):
A5: Empresas!Incluir — SI/NO. NO saca la empresa del juego.
A6: Empresas!Rareza manual — fuerza una rareza (Legendaria, Épica, Rara, Poco común, Común). Vacío = automática.
A7: Umbrales!B2:B6 — capitalización mínima (M USD) de cada rareza.
A8: Umbrales!C2:C6 — probabilidad de cada rareza en el gacha (deben sumar 100 %).
A9: Umbrales!B9:B10 — coeficiente y exponente de la fórmula de ingresos.
A10: FX!B — tipo de cambio a USD.
A12: Después de editar, ejecuta: npm run data (o python scripts/build_data.py) para regenerar el JSON del juego.
A13: Los umbrales y la fórmula de ingresos también están en src/game/balance.ts; mantenlos iguales.
A14: Nota: la moneda GBp (peniques) se normaliza a GBP porque Yahoo da la capitalización ya en libras.

Sheet Empresas
A1: Ticker | B1: Nombre | C1: País | D1: Código país | E1: Sector | F1: Industria | G1: Bolsa | H1: Moneda | I1: Cap. local (M) | J1: Tipo cambio a USD | K1: Cap. USD (M) | L1: Rareza | M1: Ingresos local (M) | N1: Beneficio local (M) | O1: Ingresos USD (M) | P1: Beneficio USD (M) | Q1: Rent. dividendo | R1: PER | S1: Índices | T1: Incluir | U1: Rareza manual | V1: Ingresos/s en juego
A2: NVDA | B2: NVIDIA Corporation | C2: United States | D2: US | E2: Tecnología | F2: Semiconductors | G2: NMS | H2: USD | I2: 5343731 | J2: =INDEX(FX!$B:$B,MATCH(H2,FX!$A:$A,0)) | K2: =I2*J2 | L2: =IF(U2<>"",U2,IF(K2>=Umbrales!$B$2,"Legendaria",IF(K2>=Umbrales!$B$3,"Épica",IF(K2>=Umbrales!$B$4,"Rara",IF(K2>=Umbrales!$B$5,"Poco común","Común"))))) | M2: 302970.01 | N2: 192880 | O2: =IF(M2="","",M2*J2) | P2: =IF(N2="","",N2*J2) | Q2: 0.0044 | R2: 28.89034 | S2: DOW30, NASDAQ100 | T2: SI | V2: =Umbrales!$B$9*(K2/1000)^Umbrales!$B$10
A3: AAPL | B3: Apple Inc. | C3: United States | D3: US | E3: Tecnología | F3: Consumer Electronics | G3: NMS | H3: USD | I3: 5005219.7 | J3: =INDEX(FX!$B:$B,MATCH(H3,FX!$A:$A,0)) | K3: =I3*J3 | L3: =IF(U3<>"",U3,IF(K3>=Umbrales!$B$2,"Legendaria",IF(K3>=Umbrales!$B$3,"Épica",IF(K3>=Umbrales!$B$4,"Rara",IF(K3>=Umbrales!$B$5,"Poco común","Común"))))) | M3: 466822.99 | N3: 128930 | O3: =IF(M3="","",M3*J3) | P3: =IF(N3="","",N3*J3) | Q3: 0.0032 | R3: 39.150684 | S3: DOW30, NASDAQ100 | T3: SI | V3: =Umbrales!$B$9*(K3/1000)^Umbrales!$B$10
A4: GOOGL | B4: Alphabet Inc. | C4: United States | D4: US | E4: Comunicación | F4: Internet Content & Information | G4: NMS | H4: USD | I4: 4251614.7 | J4: =INDEX(FX!$B:$B,MATCH(H4,FX!$A:$A,0)) | K4: =I4*J4 | L4: =IF(U4<>"",U4,IF(K4>=Umbrales!$B$2,"Legendaria",IF(K4>=Umbrales!$B$3,"Épica",IF(K4>=Umbrales!$B$4,"Rara",IF(K4>=Umbrales!$B$5,"Poco común","Común"))))) | M4: 445865.98 | N4: 244118.99 | O4: =IF(M4="","",M4*J4) | P4: =IF(N4="","",N4*J4) | Q4: 0.0025 | R4: 17.754852 | S4: NASDAQ100 | T4: SI | V4: =Umbrales!$B$9*(K4/1000)^Umbrales!$B$10
A5: MSFT | B5: Microsoft Corporation | C5: United States | D5: US | E5: Tecnología | F5: Software - Infrastructure | G5: NMS | H5: USD | I5: 3962939.6 | J5: =INDEX(FX!$B:$B,MATCH(H5,FX!$A:$A,0)) | K5: =I5*J5 | L5: =IF(U5<>"",U5,IF(K5>=Umbrales!$B$2,"Legendaria",IF(K5>=Umbrales!$B$3,"Épica",IF(K5>=Umbrales!$B$4,"Rara",IF(K5>=Umbrales!$B$5,"Poco común","Común"))))) | M5: 331839.01 | N5: 133749 | O5: =IF(M5="","",M5*J5) | P5: =IF(N5="","",N5*J5) | Q5: 0.0072 | R5: 30.067043 | S5: DOW30, NASDAQ100 | T5: SI | V5: =Umbrales!$B$9*(K5/1000)^Umbrales!$B$10
A6: AMZN | B6: Amazon.com, Inc. | C6: United States | D6: US | E6: Consumo cíclico | F6: Internet Retail | G6: NMS | H6: USD | I6: 2740586.5 | J6: =INDEX(FX!$B:$B,MATCH(H6,FX!$A:$A,0)) | K6: =I6*J6 | L6: =IF(U6<>"",U6,IF(K6>=Umbrales!$B$2,"Legendaria",IF(K6>=Umbrales!$B$3,"Épica",IF(K6>=Umbrales!$B$4,"Rara",IF(K6>=Umbrales!$B$5,"Poco común","Común"))))) | M6: 775680.03 | N6: 135281 | O6: =IF(M6="","",M6*J6) | P6: =IF(N6="","",N6*J6) | Q6: 0 | R6: 20.440868 | S6: DOW30, NASDAQ100 | T6: SI | V6: =Umbrales!$B$9*(K6/1000)^Umbrales!$B$10
A7: TSM | B7: Taiwan Semiconductor Manufacturing Company Limited | C7: Taiwan | D7: TW | E7: Tecnología | F7: Semiconductors | G7: NYQ | H7: USD | I7: 2230183.8 | J7: =INDEX(FX!$B:$B,MATCH(H7,FX!$A:$A,0)) | K7: =I7*J7 | L7: =IF(U7<>"",U7,IF(K7>=Umbrales!$B$2,"Legendaria",IF(K7>=Umbrales!$B$3,"Épica",IF(K7>=Umbrales!$B$4,"Rara",IF(K7>=Umbrales!$B$5,"Poco común","Común"))))) | M7: 4440492.3 | N7: 2216808.4 | O7: =IF(M7="","",M7*J7) | P7: =IF(N7="","",N7*J7) | Q7: 0.0085 | R7: 32.355156 | S7: ASIA_TOP | T7: SI | V7: =Umbrales!$B$9*(K7/1000)^Umbrales!$B$10
A8: META | B8: Meta Platforms, Inc. | C8: United States | D8: US | E8: Comunicación | F8: Internet Content & Information | G8: NMS | H8: USD | I8: 1878887.6 | J8: =INDEX(FX!$B:$B,MATCH(H8,FX!$A:$A,0)) | K8: =I8*J8 | L8: =IF(U8<>"",U8,IF(K8>=Umbrales!$B$2,"Legendaria",IF(K8>=Umbrales!$B$3,"Épica",IF(K8>=Umbrales!$B$4,"Rara",IF(K8>=Umbrales!$B$5,"Poco común","Común"))))) | M8: 228246.99 | N8: 68097.999 | O8: =IF(M8="","",M8*J8) | P8: =IF(N8="","",N8*J8) | Q8: 0.0028 | R8: 27.78975 | S8: NASDAQ100 | T8: SI | V8: =Umbrales!$B$9*(K8/1000)^Umbrales!$B$10
A9: AVGO | B9: Broadcom Inc. | C9: United States | D9: US | E9: Tecnología | F9: Semiconductors | G9: NMS | H9: USD | I9: 1652869.4 | J9: =INDEX(FX!$B:$B,MATCH(H9,FX!$A:$A,0)) | K9: =I9*J9 | L9: =IF(U9<>"",U9,IF(K9>=Umbrales!$B$2,"Legendaria",IF(K9>=Umbrales!$B$3,"Épica",IF(K9>=Umbrales!$B$4,"Rara",IF(K9>=Umbrales!$B$5,"Poco común","Común"))))) | M9: 89103.999 | N9: 38265 | O9: =IF(M9="","",M9*J9) | P9: =IF(N9="","",N9*J9) | Q9: 0.0073 | R9: 45.619236 | S9: NASDAQ100 | T9: SI | V9: =Umbrales!$B$9*(K9/1000)^Umbrales!$B$10
A10: 2222.SR | B10: Saudi Arabian Oil Company | C10: Saudi Arabia | D10: SA | E10: Energía | F10: Oil & Gas Integrated | G10: SAU | H10: SAR | I10: 6110580.8 | J10: =INDEX(FX!$B:$B,MATCH(H10,FX!$A:$A,0)) | K10: =I10*J10 | L10: =IF(U10<>"",U10,IF(K10>=Umbrales!$B$2,"Legendaria",IF(K10>=Umbrales!$B$3,"Épica",IF(K10>=Umbrales!$B$4,"Rara",IF(K10>=Umbrales!$B$5,"Poco común","Común"))))) | M10: 1823483 | N10: 408371 | O10: =IF(M10="","",M10*J10) | P10: =IF(N10="","",N10*J10) | Q10: 0.0535 | R10: 14.686047 | S10: ASIA_TOP | T10: SI | V10: =Umbrales!$B$9*(K10/1000)^Umbrales!$B$10
A11: TSLA | B11: Tesla, Inc. | C11: United States | D11: US | E11: Consumo cíclico | F11: Auto Manufacturers | G11: NMS | H11: USD | I11: 1450115.9 | J11: =INDEX(FX!$B:$B,MATCH(H11,FX!$A:$A,0)) | K11: =I11*J11 | L11: =IF(U11<>"",U11,IF(K11>=Umbrales!$B$2,"Legendaria",IF(K11>=Umbrales!$B$3,"Épica",IF(K11>=Umbrales!$B$4,"Rara",IF(K11>=Umbrales!$B$5,"Poco común","Común"))))) | M11: 103619 | N11: 3806.0001 | O11: =IF(M11="","",M11*J11) | P11: =IF(N11="","",N11*J11) | Q11: 0 | R11: 339.96295 | S11: NASDAQ100 | T11: SI | V11: =Umbrales!$B$9*(K11/1000)^Umbrales!$B$10
A12: BRK-B | B12: Berkshire Hathaway Inc. | C12: United States | D12: US | E12: Finanzas | F12: Insurance - Diversified | G12: NYQ | H12: USD | I12: 1126762.5 | J12: =INDEX(FX!$B:$B,MATCH(H12,FX!$A:$A,0)) | K12: =I12*J12 | L12: =IF(U12<>"",U12,IF(K12>=Umbrales!$B$2,"Legendaria",IF(K12>=Umbrales!$B$3,"Épica",IF(K12>=Umbrales!$B$4,"Rara",IF(K12>=Umbrales!$B$5,"Poco común","Común"))))) | M12: 384687.01 | N12: 85768.004 | O12: =IF(M12="","",M12*J12) | P12: =IF(N12="","",N12*J12) | Q12: 0 | R12: 13.093283 | T12: SI | V12: =Umbrales!$B$9*(K12/1000)^Umbrales!$B$10
A13: LLY | B13: Eli Lilly and Company | C13: United States | D13: US | E13: Salud | F13: Drug Manufacturers - General | G13: NYQ | H13: USD | I13: 1077418.9 | J13: =INDEX(FX!$B:$B,MATCH(H13,FX!$A:$A,0)) | K13: =I13*J13 | L13: =IF(U13<>"",U13,IF(K13>=Umbrales!$B$2,"Legendaria",IF(K13>=Umbrales!$B$3,"Épica",IF(K13>=Umbrales!$B$4,"Rara",IF(K13>=Umbrales!$B$5,"Poco común","Común"))))) | M13: 79666.004 | N13: 26710.999 | O13: =IF(M13="","",M13*J13) | P13: =IF(N13="","",N13*J13) | Q13: 0.0059 | R13: 39.155815 | T13: SI | V13: =Umbrales!$B$9*(K13/1000)^Umbrales!$B$10
A14: MU | B14: Micron Technology, Inc. | C14: United States | D14: US | E14: Tecnología | F14: Semiconductors | G14: NMS | H14: USD | I14: 1034267.9 | J14: =INDEX(FX!$B:$B,MATCH(H14,FX!$A:$A,0)) | K14: =I14*J14 | L14: =IF(U14<>"",U14,IF(K14>=Umbrales!$B$2,"Legendaria",IF(K14>=Umbrales!$B$3,"Épica",IF(K14>=Umbrales!$B$4,"Rara",IF(K14>=Umbrales!$B$5,"Poco común","Común"))))) | M14: 133188 | N14: 84968.997 | O14: =IF(M14="","",M14*J14) | P14: =IF(N14="","",N14*J14) | Q14: 0.0006 | R14: 12.824495 | S14: NASDAQ100 | T14: SI | V14: =Umbrales!$B$9*(K14/1000)^Umbrales!$B$10
A15: 005930.KS | B15: Samsung Electronics Co., Ltd. | C15: South Korea | D15: KR | E15: Tecnología | F15: Consumer Electronics | G15: KSC | H15: KRW | I15: 1.3675038e+09 | J15: =INDEX(FX!$B:$B,MATCH(H15,FX!$A:$A,0)) | K15: =I15*J15 | L15: =IF(U15<>"",U15,IF(K15>=Umbrales!$B$2,"Legendaria",IF(K15>=Umbrales!$B$3,"Épica",IF(K15>=Umbrales!$B$4,"Rara",IF(K15>=Umbrales!$B$5,"Poco común","Común"))))) | M15: 4.8527205e+08 | N15: 1.3526468e+08 | O15: =IF(M15="","",M15*J15) | P15: =IF(N15="","",N15*J15) | Q15: 0.0064 | S15: ASIA_TOP | T15: SI | V15: =Umbrales!$B$9*(K15/1000)^Umbrales!$B$10
A16: AMD | B16: Advanced Micro Devices, Inc. | C16: United States | D16: US | E16: Tecnología | F16: Semiconductors | G16: NMS | H16: USD | I16: 931849.37 | J16: =INDEX(FX!$B:$B,MATCH(H16,FX!$A:$A,0)) | K16: =I16*J16 | L16: =IF(U16<>"",U16,IF(K16>=Umbrales!$B$2,"Legendaria",IF(K16>=Umbrales!$B$3,"Épica",IF(K16>=Umbrales!$B$4,"Rara",IF(K16>=Umbrales!$B$5,"Poco común","Común"))))) | M16: 41305.002 | N16: 6469.0002 | O16: =IF(M16="","",M16*J16) | P16: =IF(N16="","",N16*J16) | Q16: 0 | R16: 145.61734 | S16: NASDAQ100 | T16: SI | V16: =Umbrales!$B$9*(K16/1000)^Umbrales!$B$10
A17: WMT | B17: Walmart Inc. | C17: United States | D17: US | E17: Consumo básico | F17: Discount Stores | G17: NMS | H17: USD | I17: 921584.01 | J17: =INDEX(FX!$B:$B,MATCH(H17,FX!$A:$A,0)) | K17: =I17*J17 | L17: =IF(U17<>"",U17,IF(K17>=Umbrales!$B$2,"Legendaria",IF(K17>=Umbrales!$B$3,"Épica",IF(K17>=Umbrales!$B$4,"Rara",IF(K17>=Umbrales!$B$5,"Poco común","Común"))))) | M17: 735839.98 | N17: 22076 | O17: =IF(M17="","",M17*J17) | P17: =IF(N17="","",N17*J17) | Q17: 0.0088 | R17: 42.08696 | S17: DOW30 | T17: SI | V17: =Umbrales!$B$9*(K17/1000)^Umbrales!$B$10
A18: JPM | B18: JPMorgan Chase & Co. | C18: United States | D18: US | E18: Finanzas | F18: Banks - Diversified | G18: NYQ | H18: USD | I18: 890369.61 | J18: =INDEX(FX!$B:$B,MATCH(H18,FX!$A:$A,0)) | K18: =I18*J18 | L18: =IF(U18<>"",U18,IF(K18>=Umbrales!$B$2,"Legendaria",IF(K18>=Umbrales!$B$3,"Épica",IF(K18>=Umbrales!$B$4,"Rara",IF(K18>=Umbrales!$B$5,"Poco común","Común"))))) | M18: 190732.99 | N18: 64527 | O18: =IF(M18="","",M18*J18) | P18: =IF(N18="","",N18*J18) | Q18: 0.0199 | R18: 13.900497 | S18: DOW30 | T18: SI | V18: =Umbrales!$B$9*(K18/1000)^Umbrales!$B$10
A19: V | B19: Visa Inc. | C19: United States | D19: US | E19: Finanzas | F19: Credit Services | G19: NYQ | H19: USD | I19: 734853.14 | J19: =INDEX(FX!$B:$B,MATCH(H19,FX!$A:$A,0)) | K19: =I19*J19 | L19: =IF(U19<>"",U19,IF(K19>=Umbrales!$B$2,"Legendaria",IF(K19>=Umbrales!$B$3,"Épica",IF(K19>=Umbrales!$B$4,"Rara",IF(K19>=Umbrales!$B$5,"Poco común","Común"))))) | M19: 44487.999 | N19: 22397.999 | O19: =IF(M19="","",M19*J19) | P19: =IF(N19="","",N19*J19) | Q19: 0.0068 | R19: 33.31319 | S19: DOW30 | T19: SI | V19: =Umbrales!$B$9*(K19/1000)^Umbrales!$B$10
A20: XOM | B20: ExxonMobil Holdings Corporation | C20: United States | D20: US | E20: Energía | F20: Oil & Gas Integrated | G20: NYQ | H20: USD | I20: 727849.5 | J20: =INDEX(FX!$B:$B,MATCH(H20,FX!$A:$A,0)) | K20: =I20*J20 | L20: =IF(U20<>"",U20,IF(K20>=Umbrales!$B$2,"Legendaria",IF(K20>=Umbrales!$B$3,"Épica",IF(K20>=Umbrales!$B$4,"Rara",IF(K20>=Umbrales!$B$5,"Poco común","Común"))))) | M20: 361060.01 | N20: 32757 | O20: =IF(M20="","",M20*J20) | P20: =IF(N20="","",N20*J20) | Q20: 0.0237 | R20: 22.406328 | T20: SI | V20: =Umbrales!$B$9*(K20/1000)^Umbrales!$B$10
A21: 000660.KS | B21: SK hynix Inc. | C21: South Korea | D21: KR | E21: Tecnología | F21: Semiconductors | G21: KSC | H21: KRW | I21: 8.9737731e+08 | J21: =INDEX(FX!$B:$B,MATCH(H21,FX!$A:$A,0)) | K21: =I21*J21 | L21: =IF(U21<>"",U21,IF(K21>=Umbrales!$B$2,"Legendaria",IF(K21>=Umbrales!$B$3,"Épica",IF(K21>=Umbrales!$B$4,"Rara",IF(K21>=Umbrales!$B$5,"Poco común","Común"))))) | M21: 1.8917061e+08 | N21: 1.619654e+08 | O21: =IF(M21="","",M21*J21) | P21: =IF(N21="","",N21*J21) | Q21: 0.0011 | S21: ASIA_TOP | T21: SI | V21: =Umbrales!$B$9*(K21/1000)^Umbrales!$B$10
A22: ASML.AS | B22: ASML Holding N.V. | C22: Netherlands | D22: NL | E22: Tecnología | F22: Semiconductor Equipment & Materials | G22: AMS | H22: EUR | I22: 553027.17 | J22: =INDEX(FX!$B:$B,MATCH(H22,FX!$A:$A,0)) | K22: =I22*J22 | L22: =IF(U22<>"",U22,IF(K22>=Umbrales!$B$2,"Legendaria",IF(K22>=Umbrales!$B$3,"Épica",IF(K22>=Umbrales!$B$4,"Rara",IF(K22>=Umbrales!$B$5,"Poco común","Común"))))) | M22: 35327.5 | N22: 10638.399 | O22: =IF(M22="","",M22*J22) | P22: =IF(N22="","",N22*J22) | Q22: 0.0052 | R22: 54.51723 | S22: EUROSTOXX50, NASDAQ100 | T22: SI | V22: =Umbrales!$B$9*(K22/1000)^Umbrales!$B$10
A23: JNJ | B23: Johnson & Johnson | C23: United States | D23: US | E23: Salud | F23: Drug Manufacturers - General | G23: NYQ | H23: USD | I23: 611897.31 | J23: =INDEX(FX!$B:$B,MATCH(H23,FX!$A:$A,0)) | K23: =I23*J23 | L23: =IF(U23<>"",U23,IF(K23>=Umbrales!$B$2,"Legendaria",IF(K23>=Umbrales!$B$3,"Épica",IF(K23>=Umbrales!$B$4,"Rara",IF(K23>=Umbrales!$B$5,"Poco común","Común"))))) | M23: 97929.003 | N23: 21037.001 | O23: =IF(M23="","",M23*J23) | P23: =IF(N23="","",N23*J23) | Q23: 0.0216 | R23: 28.820658 | S23: DOW30 | T23: SI | V23: =Umbrales!$B$9*(K23/1000)^Umbrales!$B$10
A24: MA | B24: Mastercard Incorporated | C24: United States | D24: US | E24: Finanzas | F24: Credit Services | G24: NYQ | H24: USD | I24: 528444.23 | J24: =INDEX(FX!$B:$B,MATCH(H24,FX!$A:$A,0)) | K24: =I24*J24 | L24: =IF(U24<>"",U24,IF(K24>=Umbrales!$B$2,"Legendaria",IF(K24>=Umbrales!$B$3,"Épica",IF(K24>=Umbrales!$B$4,"Rara",IF(K24>=Umbrales!$B$5,"Poco común","Común"))))) | M24: 35083.002 | N24: 16257 | O24: =IF(M24="","",M24*J24) | P24: =IF(N24="","",N24*J24) | Q24: 0.0058 | R24: 33.18152 | T24: SI | V24: =Umbrales!$B$9*(K24/1000)^Umbrales!$B$10
A25: INTC | B25: Intel Corporation | C25: United States | D25: US | E25: Tecnología | F25: Semiconductors | G25: NMS | H25: USD | I25: 518672.65 | J25: =INDEX(FX!$B:$B,MATCH(H25,FX!$A:$A,0)) | K25: =I25*J25 | L25: =IF(U25<>"",U25,IF(K25>=Umbrales!$B$2,"Legendaria",IF(K25>=Umbrales!$B$3,"Épica",IF(K25>=Umbrales!$B$4,"Rara",IF(K25>=Umbrales!$B$5,"Poco común","Común"))))) | M25: 57031.999 | N25: -11289 | O25: =IF(M25="","",M25*J25) | P25: =IF(N25="","",N25*J25) | Q25: 0 | S25: NASDAQ100 | T25: SI | V25: =Umbrales!$B$9*(K25/1000)^Umbrales!$B$10
A26: ABBV | B26: AbbVie Inc. | C26: United States | D26: US | E26: Salud | F26: Drug Manufacturers - General | G26: NYQ | H26: USD | I26: 500942.44 | J26: =INDEX(FX!$B:$B,MATCH(H26,FX!$A:$A,0)) | K26: =I26*J26 | L26: =IF(U26<>"",U26,IF(K26>=Umbrales!$B$2,"Legendaria",IF(K26>=Umbrales!$B$3,"Épica",IF(K26>=Umbrales!$B$4,"Rara",IF(K26>=Umbrales!$B$5,"Poco común","Común"))))) | M26: 64385.999 | N26: 6270.0001 | O26: =IF(M26="","",M26*J26) | P26: =IF(N26="","",N26*J26) | Q26: 0.0252 | R26: 80.0791 | T26: SI | V26: =Umbrales!$B$9*(K26/1000)^Umbrales!$B$10
A27: PLTR | B27: Palantir Technologies Inc. | C27: United States | D27: US | E27: Tecnología | F27: Software - Infrastructure | G27: NMS | H27: USD | I27: 482942.65 | J27: =INDEX(FX!$B:$B,MATCH(H27,FX!$A:$A,0)) | K27: =I27*J27 | L27: =IF(U27<>"",U27,IF(K27>=Umbrales!$B$2,"Legendaria",IF(K27>=Umbrales!$B$3,"Épica",IF(K27>=Umbrales!$B$4,"Rara",IF(K27>=Umbrales!$B$5,"Poco común","Común"))))) | M27: 6155.9409 | N27: 3016.692 | O27: =IF(M27="","",M27*J27) | P27: =IF(N27="","",N27*J27) | Q27: 0 | R27: 173.25 | S27: NASDAQ100 | T27: SI | V27: =Umbrales!$B$9*(K27/1000)^Umbrales!$B$10
A28: 0700.HK | B28: Tencent Holdings Limited | C28: China | D28: CN | E28: Comunicación | F28: Internet Content & Information | G28: HKG | H28: HKD | I28: 3762314 | J28: =INDEX(FX!$B:$B,MATCH(H28,FX!$A:$A,0)) | K28: =I28*J28 | L28: =IF(U28<>"",U28,IF(K28>=Umbrales!$B$2,"Legendaria",IF(K28>=Umbrales!$B$3,"Épica",IF(K28>=Umbrales!$B$4,"Rara",IF(K28>=Umbrales!$B$5,"Poco común","Común"))))) | M28: 788483.01 | N28: 235508.01 | O28: =IF(M28="","",M28*J28) | P28: =IF(N28="","",N28*J28) | Q28: 0.0125 | R28: 14.706089 | S28: ASIA_TOP | T28: SI | V28: =Umbrales!$B$9*(K28/1000)^Umbrales!$B$10
A29: CSCO | B29: Cisco Systems, Inc. | C29: United States | D29: US | E29: Tecnología | F29: Communication Equipment | G29: NMS | H29: USD | I29: 448035.59 | J29: =INDEX(FX!$B:$B,MATCH(H29,FX!$A:$A,0)) | K29: =I29*J29 | L29: =IF(U29<>"",U29,IF(K29>=Umbrales!$B$2,"Legendaria",IF(K29>=Umbrales!$B$3,"Épica",IF(K29>=Umbrales!$B$4,"Rara",IF(K29>=Umbrales!$B$5,"Poco común","Común"))))) | M29: 63325 | N29: 13267 | O29: =IF(M29="","",M29*J29) | P29: =IF(N29="","",N29*J29) | Q29: 0.0146 | R29: 34.541035 | S29: DOW30, NASDAQ100 | T29: SI | V29: =Umbrales!$B$9*(K29/1000)^Umbrales!$B$10
A30: CVX | B30: Chevron Corporation | C30: United States | D30: US | E30: Energía | F30: Oil & Gas Integrated | G30: NYQ | H30: USD | I30: 435554.39 | J30: =INDEX(FX!$B:$B,MATCH(H30,FX!$A:$A,0)) | K30: =I30*J30 | L30: =IF(U30<>"",U30,IF(K30>=Umbrales!$B$2,"Legendaria",IF(K30>=Umbrales!$B$3,"Épica",IF(K30>=Umbrales!$B$4,"Rara",IF(K30>=Umbrales!$B$5,"Poco común","Común"))))) | M30: 209384 | N30: 20591 | O30: =IF(M30="","",M30*J30) | P30: =IF(N30="","",N30*J30) | Q30: 0.0327 | R30: 21.370546 | S30: DOW30 | T30: SI | V30: =Umbrales!$B$9*(K30/1000)^Umbrales!$B$10
A31: COST | B31: Costco Wholesale Corporation | C31: United States | D31: US | E31: Consumo básico | F31: Discount Stores | G31: NMS | H31: USD | I31: 435153.01 | J31: =INDEX(FX!$B:$B,MATCH(H31,FX!$A:$A,0)) | K31: =I31*J31 | L31: =IF(U31<>"",U31,IF(K31>=Umbrales!$B$2,"Legendaria",IF(K31>=Umbrales!$B$3,"Épica",IF(K31>=Umbrales!$B$4,"Rara",IF(K31>=Umbrales!$B$5,"Poco común","Común"))))) | M31: 303154 | N31: 9226.0004 | O31: =IF(M31="","",M31*J31) | P31: =IF(N31="","",N31*J31) | Q31: 0.0062 | R31: 47.302505 | S31: NASDAQ100 | T31: SI | V31: =Umbrales!$B$9*(K31/1000)^Umbrales!$B$10
A32: ORCL | B32: Oracle Corporation | C32: United States | D32: US | E32: Tecnología | F32: Software - Infrastructure | G32: NYQ | H32: USD | I32: 395762.47 | J32: =INDEX(FX!$B:$B,MATCH(H32,FX!$A:$A,0)) | K32: =I32*J32 | L32: =IF(U32<>"",U32,IF(K32>=Umbrales!$B$2,"Legendaria",IF(K32>=Umbrales!$B$3,"Épica",IF(K32>=Umbrales!$B$4,"Rara",IF(K32>=Umbrales!$B$5,"Poco común","Común"))))) | M32: 71776.002 | N32: 18736.001 | O32: =IF(M32="","",M32*J32) | P32: =IF(N32="","",N32*J32) | Q32: 0.014 | R32: 22.43127 | T32: SI | V32: =Umbrales!$B$9*(K32/1000)^Umbrales!$B$10
A33: KO | B33: The Coca-Cola Company | C33: United States | D33: US | E33: Consumo básico | F33: Beverages - Non-Alcoholic | G33: NYQ | H33: USD | I33: 394887.95 | J33: =INDEX(FX!$B:$B,MATCH(H33,FX!$A:$A,0)) | K33: =I33*J33 | L33: =IF(U33<>"",U33,IF(K33>=Umbrales!$B$2,"Legendaria",IF(K33>=Umbrales!$B$3,"Épica",IF(K33>=Umbrales!$B$4,"Rara",IF(K33>=Umbrales!$B$5,"Poco común","Común"))))) | M33: 50128.998 | N33: 14316 | O33: =IF(M33="","",M33*J33) | P33: =IF(N33="","",N33*J33) | Q33: 0.0235 | R33: 27.561562 | S33: DOW30 | T33: SI | V33: =Umbrales!$B$9*(K33/1000)^Umbrales!$B$10
A34: PG | B34: The Procter & Gamble Company | C34: United States | D34: US | E34: Consumo básico | F34: Household & Personal Products | G34: NYQ | H34: USD | I34: 363843.52 | J34: =INDEX(FX!$B:$B,MATCH(H34,FX!$A:$A,0)) | K34: =I34*J34 | L34: =IF(U34<>"",U34,IF(K34>=Umbrales!$B$2,"Legendaria",IF(K34>=Umbrales!$B$3,"Épica",IF(K34>=Umbrales!$B$4,"Rara",IF(K34>=Umbrales!$B$5,"Poco común","Común"))))) | M34: 87031.996 | N34: 15754 | O34: =IF(M34="","",M34*J34) | P34: =IF(N34="","",N34*J34) | Q34: 0.0284 | R34: 23.121122 | S34: DOW30 | T34: SI | V34: =Umbrales!$B$9*(K34/1000)^Umbrales!$B$10
A35: MRK | B35: Merck & Co., Inc. | C35: United States | D35: US | E35: Salud | F35: Drug Manufacturers - General | G35: NYQ | H35: USD | I35: 363587.08 | J35: =INDEX(FX!$B:$B,MATCH(H35,FX!$A:$A,0)) | K35: =I35*J35 | L35: =IF(U35<>"",U35,IF(K35>=Umbrales!$B$2,"Legendaria",IF(K35>=Umbrales!$B$3,"Épica",IF(K35>=Umbrales!$B$4,"Rara",IF(K35>=Umbrales!$B$5,"Poco común","Común"))))) | M35: 66568.999 | N35: 3172.9999 | O35: =IF(M35="","",M35*J35) | P35: =IF(N35="","",N35*J35) | Q35: 0.0239 | R35: 116.96031 | S35: DOW30 | T35: SI | V35: =Umbrales!$B$9*(K35/1000)^Umbrales!$B$10
A36: BAC | B36: Bank of America Corporation | C36: United States | D36: US | E36: Finanzas | F36: Banks - Diversified | G36: NYQ | H36: USD | I36: 359357.35 | J36: =INDEX(FX!$B:$B,MATCH(H36,FX!$A:$A,0)) | K36: =I36*J36 | L36: =IF(U36<>"",U36,IF(K36>=Umbrales!$B$2,"Legendaria",IF(K36>=Umbrales!$B$3,"Épica",IF(K36>=Umbrales!$B$4,"Rara",IF(K36>=Umbrales!$B$5,"Poco común","Común"))))) | M36: 113931 | N36: 32125 | O36: =IF(M36="","",M36*J36) | P36: =IF(N36="","",N36*J36) | Q36: 0.0237 | R36: 12.473301 | T36: SI | V36: =Umbrales!$B$9*(K36/1000)^Umbrales!$B$10
A37: LRCX | B37: Lam Research Corporation | C37: United States | D37: US | E37: Tecnología | F37: Semiconductor Equipment & Materials | G37: NMS | H37: USD | I37: 359058.7 | J37: =INDEX(FX!$B:$B,MATCH(H37,FX!$A:$A,0)) | K37: =I37*J37 | L37: =IF(U37<>"",U37,IF(K37>=Umbrales!$B$2,"Legendaria",IF(K37>=Umbrales!$B$3,"Épica",IF(K37>=Umbrales!$B$4,"Rara",IF(K37>=Umbrales!$B$5,"Poco común","Común"))))) | M37: 23232.69 | N37: 7265.3962 | O37: =IF(M37="","",M37*J37) | P37: =IF(N37="","",N37*J37) | Q37: 0.0044 | R37: 49.8125 | S37: NASDAQ100 | T37: SI | V37: =Umbrales!$B$9*(K37/1000)^Umbrales!$B$10
A38: UNH | B38: UnitedHealth Group Incorporated | C38: United States | D38: US | E38: Salud | F38: Healthcare Plans | G38: NYQ | H38: USD | I38: 355106.46 | J38: =INDEX(FX!$B:$B,MATCH(H38,FX!$A:$A,0)) | K38: =I38*J38 | L38: =IF(U38<>"",U38,IF(K38>=Umbrales!$B$2,"Legendaria",IF(K38>=Umbrales!$B$3,"Épica",IF(K38>=Umbrales!$B$4,"Rara",IF(K38>=Umbrales!$B$5,"Poco común","Común"))))) | M38: 450059.01 | N38: 15884 | O38: =IF(M38="","",M38*J38) | P38: =IF(N38="","",N38*J38) | Q38: 0.0246 | R38: 24.286064 | S38: DOW30 | T38: SI | V38: =Umbrales!$B$9*(K38/1000)^Umbrales!$B$10
A39: AMAT | B39: Applied Materials, Inc. | C39: United States | D39: US | E39: Tecnología | F39: Semiconductor Equipment & Materials | G39: NMS | H39: USD | I39: 354444.44 | J39: =INDEX(FX!$B:$B,MATCH(H39,FX!$A:$A,0)) | K39: =I39*J39 | L39: =IF(U39<>"",U39,IF(K39>=Umbrales!$B$2,"Legendaria",IF(K39>=Umbrales!$B$3,"Épica",IF(K39>=Umbrales!$B$4,"Rara",IF(K39>=Umbrales!$B$5,"Poco común","Común"))))) | M39: 30837 | N39: 9267.0003 | O39: =IF(M39="","",M39*J39) | P39: =IF(N39="","",N39*J39) | Q39: 0.0046 | R39: 40.056503 | S39: NASDAQ100 | T39: SI | V39: =Umbrales!$B$9*(K39/1000)^Umbrales!$B$10
A40: 1398.HK | B40: Industrial and Commercial Bank of China Limited | C40: China | D40: CN | E40: Finanzas | F40: Banks - Diversified | G40: HKG | H40: HKD | I40: 2742546.3 | J40: =INDEX(FX!$B:$B,MATCH(H40,FX!$A:$A,0)) | K40: =I40*J40 | L40: =IF(U40<>"",U40,IF(K40>=Umbrales!$B$2,"Legendaria",IF(K40>=Umbrales!$B$3,"Épica",IF(K40>=Umbrales!$B$4,"Rara",IF(K40>=Umbrales!$B$5,"Poco común","Común"))))) | M40: 682491.97 | N40: 361632.01 | O40: =IF(M40="","",M40*J40) | P40: =IF(N40="","",N40*J40) | Q40: 0.0491 | R40: 6.809735 | S40: ASIA_TOP | T40: SI | V40: =Umbrales!$B$9*(K40/1000)^Umbrales!$B$10
A41: CAT | B41: Caterpillar Inc. | C41: United States | D41: US | E41: Industria | F41: Farm & Heavy Construction Machinery | G41: NYQ | H41: USD | I41: 344287.28 | J41: =INDEX(FX!$B:$B,MATCH(H41,FX!$A:$A,0)) | K41: =I41*J41 | L41: =IF(U41<>"",U41,IF(K41>=Umbrales!$B$2,"Legendaria",IF(K41>=Umbrales!$B$3,"Épica",IF(K41>=Umbrales!$B$4,"Rara",IF(K41>=Umbrales!$B$5,"Poco común","Común"))))) | M41: 74728.997 | N41: 10844 | O41: =IF(M41="","",M41*J41) | P41: =IF(N41="","",N41*J41) | Q41: 0.0084 | R41: 33.273212 | S41: DOW30 | T41: SI | V41: =Umbrales!$B$9*(K41/1000)^Umbrales!$B$10
A42: DELL | B42: Dell Technologies Inc. | C42: United States | D42: US | E42: Tecnología | F42: Computer Hardware | G42: NYQ | H42: USD | I42: 322948.37 | J42: =INDEX(FX!$B:$B,MATCH(H42,FX!$A:$A,0)) | K42: =I42*J42 | L42: =IF(U42<>"",U42,IF(K42>=Umbrales!$B$2,"Legendaria",IF(K42>=Umbrales!$B$3,"Épica",IF(K42>=Umbrales!$B$4,"Rara",IF(K42>=Umbrales!$B$5,"Poco común","Común"))))) | M42: 151197.01 | N42: 11378 | O42: =IF(M42="","",M42*J42) | P42: =IF(N42="","",N42*J42) | Q42: 0.0044 | R42: 29.530811 | T42: SI | V42: =Umbrales!$B$9*(K42/1000)^Umbrales!$B$10
A43: HSBA.L | B43: HSBC Holdings plc | C43: United Kingdom | D43: GB | E43: Finanzas | F43: Banks - Diversified | G43: LSE | H43: GBP | I43: 242443.03 | J43: =INDEX(FX!$B:$B,MATCH(H43,FX!$A:$A,0)) | K43: =I43*J43 | L43: =IF(U43<>"",U43,IF(K43>=Umbrales!$B$2,"Legendaria",IF(K43>=Umbrales!$B$3,"Épica",IF(K43>=Umbrales!$B$4,"Rara",IF(K43>=Umbrales!$B$5,"Poco común","Común"))))) | M43: 67432.002 | N43: 21102 | O43: =IF(M43="","",M43*J43) | P43: =IF(N43="","",N43*J43) | Q43: 0.0389 | R43: 13.632693 | S43: UK_TOP | T43: SI | V43: =Umbrales!$B$9*(K43/1000)^Umbrales!$B$10
A44: PM | B44: Philip Morris International Inc. | C44: United States | D44: US | E44: Consumo básico | F44: Tobacco | G44: NYQ | H44: USD | I44: 320419.73 | J44: =INDEX(FX!$B:$B,MATCH(H44,FX!$A:$A,0)) | K44: =I44*J44 | L44: =IF(U44<>"",U44,IF(K44>=Umbrales!$B$2,"Legendaria",IF(K44>=Umbrales!$B$3,"Épica",IF(K44>=Umbrales!$B$4,"Rara",IF(K44>=Umbrales!$B$5,"Poco común","Común"))))) | M44: 42545 | N44: 10844 | O44: =IF(M44="","",M44*J44) | P44: =IF(N44="","",N44*J44) | Q44: 0.0321 | R44: 28.632313 | T44: SI | V44: =Umbrales!$B$9*(K44/1000)^Umbrales!$B$10
A45: GE | B45: GE Aerospace | C45: United States | D45: US | E45: Industria | F45: Aerospace & Defense | G45: NYQ | H45: USD | I45: 318552.44 | J45: =INDEX(FX!$B:$B,MATCH(H45,FX!$A:$A,0)) | K45: =I45*J45 | L45: =IF(U45<>"",U45,IF(K45>=Umbrales!$B$2,"Legendaria",IF(K45>=Umbrales!$B$3,"Épica",IF(K45>=Umbrales!$B$4,"Rara",IF(K45>=Umbrales!$B$5,"Poco común","Común"))))) | M45: 50639 | N45: 8963.9997 | O45: =IF(M45="","",M45*J45) | P45: =IF(N45="","",N45*J45) | Q45: 0.0061 | R45: 36.29078 | T45: SI | V45: =Umbrales!$B$9*(K45/1000)^Umbrales!$B$10
A46: PANW | B46: Palo Alto Networks, Inc. | C46: United States | D46: US | E46: Tecnología | F46: Software - Infrastructure | G46: NMS | H46: USD | I46: 306782.73 | J46: =INDEX(FX!$B:$B,MATCH(H46,FX!$A:$A,0)) | K46: =I46*J46 | L46: =IF(U46<>"",U46,IF(K46>=Umbrales!$B$2,"Legendaria",IF(K46>=Umbrales!$B$3,"Épica",IF(K46>=Umbrales!$B$4,"Rara",IF(K46>=Umbrales!$B$5,"Poco común","Común"))))) | M46: 11480.001 | N46: 307 | O46: =IF(M46="","",M46*J46) | P46: =IF(N46="","",N46*J46) | Q46: 0 | R46: 986.9474 | S46: NASDAQ100 | T46: SI | V46: =Umbrales!$B$9*(K46/1000)^Umbrales!$B$10
A47: HD | B47: The Home Depot, Inc. | C47: United States | D47: US | E47: Consumo cíclico | F47: Home Improvement Retail | G47: NYQ | H47: USD | I47: 294827.26 | J47: =INDEX(FX!$B:$B,MATCH(H47,FX!$A:$A,0)) | K47: =I47*J47 | L47: =IF(U47<>"",U47,IF(K47>=Umbrales!$B$2,"Legendaria",IF(K47>=Umbrales!$B$3,"Épica",IF(K47>=Umbrales!$B$4,"Rara",IF(K47>=Umbrales!$B$5,"Poco común","Común"))))) | M47: 169176.01 | N47: 14227 | O47: =IF(M47="","",M47*J47) | P47: =IF(N47="","",N47*J47) | Q47: 0.0317 | R47: 20.679497 | S47: DOW30 | T47: SI | V47: =Umbrales!$B$9*(K47/1000)^Umbrales!$B$10
A48: SHEL.L | B48: Shell plc | C48: United Kingdom | D48: GB | E48: Energía | F48: Oil & Gas Integrated | G48: LSE | H48: GBP | I48: 222007.93 | J48: =INDEX(FX!$B:$B,MATCH(H48,FX!$A:$A,0)) | K48: =I48*J48 | L48: =IF(U48<>"",U48,IF(K48>=Umbrales!$B$2,"Legendaria",IF(K48>=Umbrales!$B$3,"Épica",IF(K48>=Umbrales!$B$4,"Rara",IF(K48>=Umbrales!$B$5,"Poco común","Común"))))) | M48: 296600.99 | N48: 25970.999 | O48: =IF(M48="","",M48*J48) | P48: =IF(N48="","",N48*J48) | Q48: 0.0299 | R48: 11.545858 | S48: UK_TOP | T48: SI | V48: =Umbrales!$B$9*(K48/1000)^Umbrales!$B$10
A49: NFLX | B49: Netflix, Inc. | C49: United States | D49: US | E49: Comunicación | F49: Entertainment | G49: NMS | H49: USD | I49: 293849.2 | J49: =INDEX(FX!$B:$B,MATCH(H49,FX!$A:$A,0)) | K49: =I49*J49 | L49: =IF(U49<>"",U49,IF(K49>=Umbrales!$B$2,"Legendaria",IF(K49>=Umbrales!$B$3,"Épica",IF(K49>=Umbrales!$B$4,"Rara",IF(K49>=Umbrales!$B$5,"Poco común","Común"))))) | M49: 48370.766 | N49: 13649.642 | O49: =IF(M49="","",M49*J49) | P49: =IF(N49="","",N49*J49) | Q49: 0 | R49: 22.191824 | S49: NASDAQ100 | T49: SI | V49: =Umbrales!$B$9*(K49/1000)^Umbrales!$B$10
A50: MS | B50: Morgan Stanley | C50: United States | D50: US | E50: Finanzas | F50: Capital Markets | G50: NYQ | H50: USD | I50: 285073.47 | J50: =INDEX(FX!$B:$B,MATCH(H50,FX!$A:$A,0)) | K50: =I50*J50 | L50: =IF(U50<>"",U50,IF(K50>=Umbrales!$B$2,"Legendaria",IF(K50>=Umbrales!$B$3,"Épica",IF(K50>=Umbrales!$B$4,"Rara",IF(K50>=Umbrales!$B$5,"Poco común","Común"))))) | M50: 77827.998 | N50: 19547.001 | O50: =IF(M50="","",M50*J50) | P50: =IF(N50="","",N50*J50) | Q50: 0.0246 | R50: 14.661551 | T50: SI | V50: =Umbrales!$B$9*(K50/1000)^Umbrales!$B$10
A51: NOVN.SW | B51: Novartis AG | C51: Switzerland | D51: CH | E51: Salud | F51: Drug Manufacturers - General | G51: EBS | H51: CHF | I51: 235916.74 | J51: =INDEX(FX!$B:$B,MATCH(H51,FX!$A:$A,0)) | K51: =I51*J51 | L51: =IF(U51<>"",U51,IF(K51>=Umbrales!$B$2,"Legendaria",IF(K51>=Umbrales!$B$3,"Épica",IF(K51>=Umbrales!$B$4,"Rara",IF(K51>=Umbrales!$B$5,"Poco común","Común"))))) | M51: 56692.998 | N51: 12757 | O51: =IF(M51="","",M51*J51) | P51: =IF(N51="","",N51*J51) | Q51: 0.0302 | R51: 23.641905 | T51: SI | V51: =Umbrales!$B$9*(K51/1000)^Umbrales!$B$10
A52: 9988.HK | B52: Alibaba Group Holding Limited | C52: China | D52: CN | E52: Consumo cíclico | F52: Internet Retail | G52: HKG | H52: HKD | I52: 2117568.6 | J52: =INDEX(FX!$B:$B,MATCH(H52,FX!$A:$A,0)) | K52: =I52*J52 | L52: =IF(U52<>"",U52,IF(K52>=Umbrales!$B$2,"Legendaria",IF(K52>=Umbrales!$B$3,"Épica",IF(K52>=Umbrales!$B$4,"Rara",IF(K52>=Umbrales!$B$5,"Poco común","Común"))))) | M52: 1044971 | N52: 73325.003 | O52: =IF(M52="","",M52*J52) | P52: =IF(N52="","",N52*J52) | Q52: 0.0093 | R52: 26.401983 | S52: ASIA_TOP | T52: SI | V52: =Umbrales!$B$9*(K52/1000)^Umbrales!$B$10
A53: SAP.DE | B53: SAP SE | C53: Germany | D53: DE | E53: Tecnología | F53: Software - Application | G53: GER | H53: EUR | I53: 229340.38 | J53: =INDEX(FX!$B:$B,MATCH(H53,FX!$A:$A,0)) | K53: =I53*J53 | L53: =IF(U53<>"",U53,IF(K53>=Umbrales!$B$2,"Legendaria",IF(K53>=Umbrales!$B$3,"Épica",IF(K53>=Umbrales!$B$4,"Rara",IF(K53>=Umbrales!$B$5,"Poco común","Común"))))) | M53: 38192.001 | N53: 7795.9997 | O53: =IF(M53="","",M53*J53) | P53: =IF(N53="","",N53*J53) | Q53: 0.0133 | R53: 28.304842 | S53: DAX40, EUROSTOXX50 | T53: SI | V53: =Umbrales!$B$9*(K53/1000)^Umbrales!$B$10
A54: TXN | B54: Texas Instruments Incorporated | C54: United States | D54: US | E54: Tecnología | F54: Semiconductors | G54: NMS | H54: USD | I54: 256302.96 | J54: =INDEX(FX!$B:$B,MATCH(H54,FX!$A:$A,0)) | K54: =I54*J54 | L54: =IF(U54<>"",U54,IF(K54>=Umbrales!$B$2,"Legendaria",IF(K54>=Umbrales!$B$3,"Épica",IF(K54>=Umbrales!$B$4,"Rara",IF(K54>=Umbrales!$B$5,"Poco común","Común"))))) | M54: 19453 | N54: 6016.9999 | O54: =IF(M54="","",M54*J54) | P54: =IF(N54="","",N54*J54) | Q54: 0.0211 | R54: 43.78315 | S54: NASDAQ100 | T54: SI | V54: =Umbrales!$B$9*(K54/1000)^Umbrales!$B$10
A55: AZN.L | B55: AstraZeneca PLC | C55: United Kingdom | D55: GB | E55: Salud | F55: Drug Manufacturers - General | G55: LSE | H55: GBP | I55: 193180.81 | J55: =INDEX(FX!$B:$B,MATCH(H55,FX!$A:$A,0)) | K55: =I55*J55 | L55: =IF(U55<>"",U55,IF(K55>=Umbrales!$B$2,"Legendaria",IF(K55>=Umbrales!$B$3,"Épica",IF(K55>=Umbrales!$B$4,"Rara",IF(K55>=Umbrales!$B$5,"Poco común","Común"))))) | M55: 61366.002 | N55: 10446 | O55: =IF(M55="","",M55*J55) | P55: =IF(N55="","",N55*J55) | Q55: 0.0201 | R55: 24.961924 | S55: NASDAQ100, UK_TOP | T55: SI | V55: =Umbrales!$B$9*(K55/1000)^Umbrales!$B$10
A56: GS | B56: The Goldman Sachs Group, Inc. | C56: United States | D56: US | E56: Finanzas | F56: Capital Markets | G56: NYQ | H56: USD | I56: 255858.11 | J56: =INDEX(FX!$B:$B,MATCH(H56,FX!$A:$A,0)) | K56: =I56*J56 | L56: =IF(U56<>"",U56,IF(K56>=Umbrales!$B$2,"Legendaria",IF(K56>=Umbrales!$B$3,"Épica",IF(K56>=Umbrales!$B$4,"Rara",IF(K56>=Umbrales!$B$5,"Poco común","Común"))))) | M56: 67570 | N56: 19982 | O56: =IF(M56="","",M56*J56) | P56: =IF(N56="","",N56*J56) | Q56: 0.0224 | R56: 12.634363 | S56: DOW30 | T56: SI | V56: =Umbrales!$B$9*(K56/1000)^Umbrales!$B$10
A57: CRWD | B57: CrowdStrike Holdings, Inc. | C57: United States | D57: US | E57: Tecnología | F57: Software - Infrastructure | G57: NMS | H57: USD | I57: 255256.71 | J57: =INDEX(FX!$B:$B,MATCH(H57,FX!$A:$A,0)) | K57: =I57*J57 | L57: =IF(U57<>"",U57,IF(K57>=Umbrales!$B$2,"Legendaria",IF(K57>=Umbrales!$B$3,"Épica",IF(K57>=Umbrales!$B$4,"Rara",IF(K57>=Umbrales!$B$5,"Poco común","Común"))))) | M57: 5396.1452 | N57: 44.995 | O57: =IF(M57="","",M57*J57) | P57: =IF(N57="","",N57*J57) | Q57: 0 | R57: 4985.8 | S57: NASDAQ100 | T57: SI | V57: =Umbrales!$B$9*(K57/1000)^Umbrales!$B$10
A58: ARM | B58: Arm Holdings plc | C58: United Kingdom | D58: GB | E58: Tecnología | F58: Semiconductors | G58: NMS | H58: USD | I58: 254194.34 | J58: =INDEX(FX!$B:$B,MATCH(H58,FX!$A:$A,0)) | K58: =I58*J58 | L58: =IF(U58<>"",U58,IF(K58>=Umbrales!$B$2,"Legendaria",IF(K58>=Umbrales!$B$3,"Épica",IF(K58>=Umbrales!$B$4,"Rara",IF(K58>=Umbrales!$B$5,"Poco común","Común"))))) | M58: 5155.9997 | N58: 1044 | O58: =IF(M58="","",M58*J58) | P58: =IF(N58="","",N58*J58) | Q58: 0 | R58: 245.37112 | S58: NASDAQ100 | T58: SI | V58: =Umbrales!$B$9*(K58/1000)^Umbrales!$B$10
A59: RTX | B59: RTX Corporation | C59: United States | D59: US | E59: Industria | F59: Aerospace & Defense | G59: NYQ | H59: USD | I59: 251316.45 | J59: =INDEX(FX!$B:$B,MATCH(H59,FX!$A:$A,0)) | K59: =I59*J59 | L59: =IF(U59<>"",U59,IF(K59>=Umbrales!$B$2,"Legendaria",IF(K59>=Umbrales!$B$3,"Épica",IF(K59>=Umbrales!$B$4,"Rara",IF(K59>=Umbrales!$B$5,"Poco común","Común"))))) | M59: 93499.998 | N59: 7737.9999 | O59: =IF(M59="","",M59*J59) | P59: =IF(N59="","",N59*J59) | Q59: 0.016 | R59: 32.20553 | T59: SI | V59: =Umbrales!$B$9*(K59/1000)^Umbrales!$B$10
A60: GEV | B60: GE Vernova Inc. | C60: United States | D60: US | E60: Industria | F60: Specialty Industrial Machinery | G60: NYQ | H60: USD | I60: 250827.65 | J60: =INDEX(FX!$B:$B,MATCH(H60,FX!$A:$A,0)) | K60: =I60*J60 | L60: =IF(U60<>"",U60,IF(K60>=Umbrales!$B$2,"Legendaria",IF(K60>=Umbrales!$B$3,"Épica",IF(K60>=Umbrales!$B$4,"Rara",IF(K60>=Umbrales!$B$5,"Poco común","Común"))))) | M60: 41366.999 | N60: 9528.9999 | O60: =IF(M60="","",M60*J60) | P60: =IF(N60="","",N60*J60) | Q60: 0.002 | R60: 27.000574 | T60: SI | V60: =Umbrales!$B$9*(K60/1000)^Umbrales!$B$10
A61: NESN.SW | B61: Nestlé S.A. | C61: Switzerland | D61: CH | E61: Consumo básico | F61: Packaged Foods | G61: EBS | H61: CHF | I61: 206420.64 | J61: =INDEX(FX!$B:$B,MATCH(H61,FX!$A:$A,0)) | K61: =I61*J61 | L61: =IF(U61<>"",U61,IF(K61>=Umbrales!$B$2,"Legendaria",IF(K61>=Umbrales!$B$3,"Épica",IF(K61>=Umbrales!$B$4,"Rara",IF(K61>=Umbrales!$B$5,"Poco común","Común"))))) | M61: 88775 | N61: 7440 | O61: =IF(M61="","",M61*J61) | P61: =IF(N61="","",N61*J61) | Q61: 0.0393 | R61: 27.768166 | T61: SI | V61: =Umbrales!$B$9*(K61/1000)^Umbrales!$B$10
A62: TMO | B62: Thermo Fisher Scientific Inc. | C62: United States | D62: US | E62: Salud | F62: Diagnostics & Research | G62: NYQ | H62: USD | I62: 248913.89 | J62: =INDEX(FX!$B:$B,MATCH(H62,FX!$A:$A,0)) | K62: =I62*J62 | L62: =IF(U62<>"",U62,IF(K62>=Umbrales!$B$2,"Legendaria",IF(K62>=Umbrales!$B$3,"Épica",IF(K62>=Umbrales!$B$4,"Rara",IF(K62>=Umbrales!$B$5,"Poco común","Común"))))) | M62: 46336 | N62: 6967.0001 | O62: =IF(M62="","",M62*J62) | P62: =IF(N62="","",N62*J62) | Q62: 0.0028 | R62: 36.23251 | T62: SI | V62: =Umbrales!$B$9*(K62/1000)^Umbrales!$B$10
A63: ANET | B63: Arista Networks, Inc. | C63: United States | D63: US | E63: Tecnología | F63: Computer Hardware | G63: NYQ | H63: USD | I63: 246468.53 | J63: =INDEX(FX!$B:$B,MATCH(H63,FX!$A:$A,0)) | K63: =I63*J63 | L63: =IF(U63<>"",U63,IF(K63>=Umbrales!$B$2,"Legendaria",IF(K63>=Umbrales!$B$3,"Épica",IF(K63>=Umbrales!$B$4,"Rara",IF(K63>=Umbrales!$B$5,"Poco común","Común"))))) | M63: 10540.8 | N63: 4044.6001 | O63: =IF(M63="","",M63*J63) | P63: =IF(N63="","",N63*J63) | Q63: 0 | R63: 61.646687 | T63: SI | V63: =Umbrales!$B$9*(K63/1000)^Umbrales!$B$10
A64: 600519.SS | B64: Kweichow Moutai Co., Ltd. | C64: China | D64: CN | E64: Consumo básico | F64: Beverages - Wineries & Distilleries | G64: SHH | H64: CNY | I64: 1641319.6 | J64: =INDEX(FX!$B:$B,MATCH(H64,FX!$A:$A,0)) | K64: =I64*J64 | L64: =IF(U64<>"",U64,IF(K64>=Umbrales!$B$2,"Legendaria",IF(K64>=Umbrales!$B$3,"Épica",IF(K64>=Umbrales!$B$4,"Rara",IF(K64>=Umbrales!$B$5,"Poco común","Común"))))) | M64: 170152 | N64: 81433.985 | O64: =IF(M64="","",M64*J64) | P64: =IF(N64="","",N64*J64) | Q64: 0.0404 | R64: 20.184011 | S64: ASIA_TOP | T64: SI | V64: =Umbrales!$B$9*(K64/1000)^Umbrales!$B$10
A65: 8306.T | B65: Mitsubishi UFJ Financial Group, Inc. | C65: Japan | D65: JP | E65: Finanzas | F65: Banks - Diversified | G65: JPX | H65: JPY | I65: 38415924 | J65: =INDEX(FX!$B:$B,MATCH(H65,FX!$A:$A,0)) | K65: =I65*J65 | L65: =IF(U65<>"",U65,IF(K65>=Umbrales!$B$2,"Legendaria",IF(K65>=Umbrales!$B$3,"Épica",IF(K65>=Umbrales!$B$4,"Rara",IF(K65>=Umbrales!$B$5,"Poco común","Común"))))) | M65: 7260459.2 | N65: 1992718 | O65: =IF(M65="","",M65*J65) | P65: =IF(N65="","",N65*J65) | Q65: 0.0276 | R65: 14.433121 | S65: ASIA_TOP | T65: SI | V65: =Umbrales!$B$9*(K65/1000)^Umbrales!$B$10
A66: WFC | B66: Wells Fargo & Company | C66: United States | D66: US | E66: Finanzas | F66: Banks - Diversified | G66: NYQ | H66: USD | I66: 242832.59 | J66: =INDEX(FX!$B:$B,MATCH(H66,FX!$A:$A,0)) | K66: =I66*J66 | L66: =IF(U66<>"",U66,IF(K66>=Umbrales!$B$2,"Legendaria",IF(K66>=Umbrales!$B$3,"Épica",IF(K66>=Umbrales!$B$4,"Rara",IF(K66>=Umbrales!$B$5,"Poco común","Común"))))) | M66: 83026.002 | N66: 21615 | O66: =IF(M66="","",M66*J66) | P66: =IF(N66="","",N66*J66) | Q66: 0.024 | R66: 11.758721 | T66: SI | V66: =Umbrales!$B$9*(K66/1000)^Umbrales!$B$10
A67: OR.PA | B67: L'Oréal S.A. | C67: France | D67: FR | E67: Consumo básico | F67: Household & Personal Products | G67: PAR | H67: EUR | I67: 212533.77 | J67: =INDEX(FX!$B:$B,MATCH(H67,FX!$A:$A,0)) | K67: =I67*J67 | L67: =IF(U67<>"",U67,IF(K67>=Umbrales!$B$2,"Legendaria",IF(K67>=Umbrales!$B$3,"Épica",IF(K67>=Umbrales!$B$4,"Rara",IF(K67>=Umbrales!$B$5,"Poco común","Común"))))) | M67: 45354.799 | N67: 6306.2999 | O67: =IF(M67="","",M67*J67) | P67: =IF(N67="","",N67*J67) | Q67: 0.0186 | R67: 33.887947 | S67: EUROSTOXX50 | T67: SI | V67: =Umbrales!$B$9*(K67/1000)^Umbrales!$B$10
A68: KLAC | B68: KLA Corporation | C68: United States | D68: US | E68: Tecnología | F68: Semiconductor Equipment & Materials | G68: NMS | H68: USD | I68: 233348.2 | J68: =INDEX(FX!$B:$B,MATCH(H68,FX!$A:$A,0)) | K68: =I68*J68 | L68: =IF(U68<>"",U68,IF(K68>=Umbrales!$B$2,"Legendaria",IF(K68>=Umbrales!$B$3,"Épica",IF(K68>=Umbrales!$B$4,"Rara",IF(K68>=Umbrales!$B$5,"Poco común","Común"))))) | M68: 13579.476 | N68: 4830.7712 | O68: =IF(M68="","",M68*J68) | P68: =IF(N68="","",N68*J68) | Q68: 0.005 | R68: 50.227528 | S68: NASDAQ100 | T68: SI | V68: =Umbrales!$B$9*(K68/1000)^Umbrales!$B$10
A69: AMGN | B69: Amgen Inc. | C69: United States | D69: US | E69: Salud | F69: Drug Manufacturers - General | G69: NMS | H69: USD | I69: 230368.69 | J69: =INDEX(FX!$B:$B,MATCH(H69,FX!$A:$A,0)) | K69: =I69*J69 | L69: =IF(U69<>"",U69,IF(K69>=Umbrales!$B$2,"Legendaria",IF(K69>=Umbrales!$B$3,"Épica",IF(K69>=Umbrales!$B$4,"Rara",IF(K69>=Umbrales!$B$5,"Poco común","Común"))))) | M69: 38095 | N69: 8743.0001 | O69: =IF(M69="","",M69*J69) | P69: =IF(N69="","",N69*J69) | Q69: 0.0244 | R69: 25.638386 | S69: DOW30, NASDAQ100 | T69: SI | V69: =Umbrales!$B$9*(K69/1000)^Umbrales!$B$10
A70: SIE.DE | B70: Siemens Aktiengesellschaft | C70: Germany | D70: DE | E70: Industria | F70: Specialty Industrial Machinery | G70: GER | H70: EUR | I70: 204684.84 | J70: =INDEX(FX!$B:$B,MATCH(H70,FX!$A:$A,0)) | K70: =I70*J70 | L70: =IF(U70<>"",U70,IF(K70>=Umbrales!$B$2,"Legendaria",IF(K70>=Umbrales!$B$3,"Épica",IF(K70>=Umbrales!$B$4,"Rara",IF(K70>=Umbrales!$B$5,"Poco común","Común"))))) | M70: 81113.997 | N70: 7870.0001 | O70: =IF(M70="","",M70*J70) | P70: =IF(N70="","",N70*J70) | Q70: 0.0197 | R70: 26.422924 | S70: DAX40, EUROSTOXX50 | T70: SI | V70: =Umbrales!$B$9*(K70/1000)^Umbrales!$B$10
A71: LIN | B71: Linde plc | C71: United Kingdom | D71: GB | E71: Materiales | F71: Specialty Chemicals | G71: NMS | H71: USD | I71: 227124.94 | J71: =INDEX(FX!$B:$B,MATCH(H71,FX!$A:$A,0)) | K71: =I71*J71 | L71: =IF(U71<>"",U71,IF(K71>=Umbrales!$B$2,"Legendaria",IF(K71>=Umbrales!$B$3,"Épica",IF(K71>=Umbrales!$B$4,"Rara",IF(K71>=Umbrales!$B$5,"Poco común","Común"))))) | M71: 35449 | N71: 7244.0003 | O71: =IF(M71="","",M71*J71) | P71: =IF(N71="","",N71*J71) | Q71: 0.013 | R71: 31.766602 | S71: NASDAQ100 | T71: SI | V71: =Umbrales!$B$9*(K71/1000)^Umbrales!$B$10
A72: 7203.T | B72: Toyota Motor Corporation | C72: Japan | D72: JP | E72: Consumo cíclico | F72: Auto Manufacturers | G72: JPX | H72: JPY | I72: 35675760 | J72: =INDEX(FX!$B:$B,MATCH(H72,FX!$A:$A,0)) | K72: =I72*J72 | L72: =IF(U72<>"",U72,IF(K72>=Umbrales!$B$2,"Legendaria",IF(K72>=Umbrales!$B$3,"Épica",IF(K72>=Umbrales!$B$4,"Rara",IF(K72>=Umbrales!$B$5,"Poco común","Común"))))) | M72: 51957025 | N72: 4483797 | O72: =IF(M72="","",M72*J72) | P72: =IF(N72="","",N72*J72) | Q72: 0.0332 | R72: 8.620297 | S72: ASIA_TOP | T72: SI | V72: =Umbrales!$B$9*(K72/1000)^Umbrales!$B$10
A73: 0941.HK | B73: China Mobile Limited | C73: Hong Kong | D73: HK | E73: Comunicación | F73: Telecom Services | G73: HKG | H73: HKD | I73: 1756379.3 | J73: =INDEX(FX!$B:$B,MATCH(H73,FX!$A:$A,0)) | K73: =I73*J73 | L73: =IF(U73<>"",U73,IF(K73>=Umbrales!$B$2,"Legendaria",IF(K73>=Umbrales!$B$3,"Épica",IF(K73>=Umbrales!$B$4,"Rara",IF(K73>=Umbrales!$B$5,"Poco común","Común"))))) | M73: 1044453 | N73: 131794 | O73: =IF(M73="","",M73*J73) | P73: =IF(N73="","",N73*J73) | Q73: 0.067 | R73: 12 | S73: ASIA_TOP | T73: SI | V73: =Umbrales!$B$9*(K73/1000)^Umbrales!$B$10
A74: SHOP | B74: Shopify Inc. | C74: Canada | D74: CA | E74: Tecnología | F74: Software - Application | G74: NMS | H74: USD | I74: 221946.09 | J74: =INDEX(FX!$B:$B,MATCH(H74,FX!$A:$A,0)) | K74: =I74*J74 | L74: =IF(U74<>"",U74,IF(K74>=Umbrales!$B$2,"Legendaria",IF(K74>=Umbrales!$B$3,"Épica",IF(K74>=Umbrales!$B$4,"Rara",IF(K74>=Umbrales!$B$5,"Poco común","Común"))))) | M74: 13269 | N74: 1928 | O74: =IF(M74="","",M74*J74) | P74: =IF(N74="","",N74*J74) | Q74: 0 | R74: 118.96551 | S74: NASDAQ100 | T74: SI | V74: =Umbrales!$B$9*(K74/1000)^Umbrales!$B$10
A75: MRVL | B75: Marvell Technology, Inc. | C75: United States | D75: US | E75: Tecnología | F75: Semiconductors | G75: NMS | H75: USD | I75: 220434.27 | J75: =INDEX(FX!$B:$B,MATCH(H75,FX!$A:$A,0)) | K75: =I75*J75 | L75: =IF(U75<>"",U75,IF(K75>=Umbrales!$B$2,"Legendaria",IF(K75>=Umbrales!$B$3,"Épica",IF(K75>=Umbrales!$B$4,"Rara",IF(K75>=Umbrales!$B$5,"Poco común","Común"))))) | M75: 9450.3004 | N75: 2639.8999 | O75: =IF(M75="","",M75*J75) | P75: =IF(N75="","",N75*J75) | Q75: 0.0009 | R75: 77.86666 | S75: NASDAQ100 | T75: SI | V75: =Umbrales!$B$9*(K75/1000)^Umbrales!$B$10
A76: MC.PA | B76: LVMH Moët Hennessy - Louis Vuitton, Société Européenne | C76: France | D76: FR | E76: Consumo cíclico | F76: Luxury Goods | G76: PAR | H76: EUR | I76: 194006.45 | J76: =INDEX(FX!$B:$B,MATCH(H76,FX!$A:$A,0)) | K76: =I76*J76 | L76: =IF(U76<>"",U76,IF(K76>=Umbrales!$B$2,"Legendaria",IF(K76>=Umbrales!$B$3,"Épica",IF(K76>=Umbrales!$B$4,"Rara",IF(K76>=Umbrales!$B$5,"Poco común","Común"))))) | M76: 79641.002 | N76: 10877 | O76: =IF(M76="","",M76*J76) | P76: =IF(N76="","",N76*J76) | Q76: 0.0339 | R76: 17.937555 | S76: EUROSTOXX50 | T76: SI | V76: =Umbrales!$B$9*(K76/1000)^Umbrales!$B$10
A77: IBM | B77: International Business Machines Corporation | C77: United States | D77: US | E77: Tecnología | F77: Information Technology Services | G77: NYQ | H77: USD | I77: 214693.59 | J77: =INDEX(FX!$B:$B,MATCH(H77,FX!$A:$A,0)) | K77: =I77*J77 | L77: =IF(U77<>"",U77,IF(K77>=Umbrales!$B$2,"Legendaria",IF(K77>=Umbrales!$B$3,"Épica",IF(K77>=Umbrales!$B$4,"Rara",IF(K77>=Umbrales!$B$5,"Poco común","Común"))))) | M77: 69094.998 | N77: 10705 | O77: =IF(M77="","",M77*J77) | P77: =IF(N77="","",N77*J77) | Q77: 0.0293 | R77: 20.511251 | S77: DOW30 | T77: SI | V77: =Umbrales!$B$9*(K77/1000)^Umbrales!$B$10
A78: AXP | B78: American Express Company | C78: United States | D78: US | E78: Finanzas | F78: Credit Services | G78: NYQ | H78: USD | I78: 207286.35 | J78: =INDEX(FX!$B:$B,MATCH(H78,FX!$A:$A,0)) | K78: =I78*J78 | L78: =IF(U78<>"",U78,IF(K78>=Umbrales!$B$2,"Legendaria",IF(K78>=Umbrales!$B$3,"Épica",IF(K78>=Umbrales!$B$4,"Rara",IF(K78>=Umbrales!$B$5,"Poco común","Común"))))) | M78: 70912.999 | N78: 11311 | O78: =IF(M78="","",M78*J78) | P78: =IF(N78="","",N78*J78) | Q78: 0.0123 | R78: 18.796694 | S78: DOW30 | T78: SI | V78: =Umbrales!$B$9*(K78/1000)^Umbrales!$B$10
A79: C | B79: Citigroup Inc. | C79: United States | D79: US | E79: Finanzas | F79: Banks - Diversified | G79: NYQ | H79: USD | I79: 205100.19 | J79: =INDEX(FX!$B:$B,MATCH(H79,FX!$A:$A,0)) | K79: =I79*J79 | L79: =IF(U79<>"",U79,IF(K79>=Umbrales!$B$2,"Legendaria",IF(K79>=Umbrales!$B$3,"Épica",IF(K79>=Umbrales!$B$4,"Rara",IF(K79>=Umbrales!$B$5,"Poco común","Común"))))) | M79: 81711.997 | N79: 16460 | O79: =IF(M79="","",M79*J79) | P79: =IF(N79="","",N79*J79) | Q79: 0.0203 | R79: 12.142006 | T79: SI | V79: =Umbrales!$B$9*(K79/1000)^Umbrales!$B$10
A80: BHP.AX | B80: BHP Group Limited | C80: Australia | D80: AU | E80: Materiales | F80: Other Industrial Metals & Mining | G80: ASX | H80: AUD | I80: 294811.3 | J80: =INDEX(FX!$B:$B,MATCH(H80,FX!$A:$A,0)) | K80: =I80*J80 | L80: =IF(U80<>"",U80,IF(K80>=Umbrales!$B$2,"Legendaria",IF(K80>=Umbrales!$B$3,"Épica",IF(K80>=Umbrales!$B$4,"Rara",IF(K80>=Umbrales!$B$5,"Poco común","Común"))))) | M80: 58759.999 | N80: 9832.9999 | O80: =IF(M80="","",M80*J80) | P80: =IF(N80="","",N80*J80) | Q80: 0.0397 | R80: 20.4947 | S80: ASIA_TOP | T80: SI | V80: =Umbrales!$B$9*(K80/1000)^Umbrales!$B$10
A81: APH | B81: Amphenol Corporation | C81: United States | D81: US | E81: Tecnología | F81: Electronic Components | G81: NYQ | H81: USD | I81: 203910.81 | J81: =INDEX(FX!$B:$B,MATCH(H81,FX!$A:$A,0)) | K81: =I81*J81 | L81: =IF(U81<>"",U81,IF(K81>=Umbrales!$B$2,"Legendaria",IF(K81>=Umbrales!$B$3,"Épica",IF(K81>=Umbrales!$B$4,"Rara",IF(K81>=Umbrales!$B$5,"Poco común","Común"))))) | M81: 29011.599 | N81: 5143.3999 | O81: =IF(M81="","",M81*J81) | P81: =IF(N81="","",N81*J81) | Q81: 0.0058 | R81: 42.844563 | T81: SI | V81: =Umbrales!$B$9*(K81/1000)^Umbrales!$B$10
A82: TTE.PA | B82: TotalEnergies SE | C82: France | D82: FR | E82: Energía | F82: Oil & Gas Integrated | G82: PAR | H82: EUR | I82: 178282.46 | J82: =INDEX(FX!$B:$B,MATCH(H82,FX!$A:$A,0)) | K82: =I82*J82 | L82: =IF(U82<>"",U82,IF(K82>=Umbrales!$B$2,"Legendaria",IF(K82>=Umbrales!$B$3,"Épica",IF(K82>=Umbrales!$B$4,"Rara",IF(K82>=Umbrales!$B$5,"Poco común","Común"))))) | M82: 196382 | N82: 17837.001 | O82: =IF(M82="","",M82*J82) | P82: =IF(N82="","",N82*J82) | Q82: 0.0451 | R82: 11.804379 | S82: EUROSTOXX50 | T82: SI | V82: =Umbrales!$B$9*(K82/1000)^Umbrales!$B$10
A83: SAN.MC | B83: Banco Santander, S.A. | C83: Spain | D83: ES | E83: Finanzas | F83: Banks - Diversified | G83: MCE | H83: EUR | I83: 174499.68 | J83: =INDEX(FX!$B:$B,MATCH(H83,FX!$A:$A,0)) | K83: =I83*J83 | L83: =IF(U83<>"",U83,IF(K83>=Umbrales!$B$2,"Legendaria",IF(K83>=Umbrales!$B$3,"Épica",IF(K83>=Umbrales!$B$4,"Rara",IF(K83>=Umbrales!$B$5,"Poco común","Común"))))) | M83: 48533 | N83: 12900 | O83: =IF(M83="","",M83*J83) | P83: =IF(N83="","",N83*J83) | Q83: 0.0209 | R83: 13.715909 | S83: EUROSTOXX50, IBEX35 | T83: SI | V83: =Umbrales!$B$9*(K83/1000)^Umbrales!$B$10
A84: ADI | B84: Analog Devices, Inc. | C84: United States | D84: US | E84: Tecnología | F84: Semiconductors | G84: NMS | H84: USD | I84: 195556.1 | J84: =INDEX(FX!$B:$B,MATCH(H84,FX!$A:$A,0)) | K84: =I84*J84 | L84: =IF(U84<>"",U84,IF(K84>=Umbrales!$B$2,"Legendaria",IF(K84>=Umbrales!$B$3,"Épica",IF(K84>=Umbrales!$B$4,"Rara",IF(K84>=Umbrales!$B$5,"Poco común","Común"))))) | M84: 13881.744 | N84: 4135.0039 | O84: =IF(M84="","",M84*J84) | P84: =IF(N84="","",N84*J84) | Q84: 0.0106 | R84: 49.27595 | S84: NASDAQ100 | T84: SI | V84: =Umbrales!$B$9*(K84/1000)^Umbrales!$B$10
A85: CRM | B85: Salesforce, Inc. | C85: United States | D85: US | E85: Tecnología | F85: Software - Application | G85: NYQ | H85: USD | I85: 194186.85 | J85: =INDEX(FX!$B:$B,MATCH(H85,FX!$A:$A,0)) | K85: =I85*J85 | L85: =IF(U85<>"",U85,IF(K85>=Umbrales!$B$2,"Legendaria",IF(K85>=Umbrales!$B$3,"Épica",IF(K85>=Umbrales!$B$4,"Rara",IF(K85>=Umbrales!$B$5,"Poco común","Común"))))) | M85: 43938.001 | N85: 9662.0001 | O85: =IF(M85="","",M85*J85) | P85: =IF(N85="","",N85*J85) | Q85: 0.0074 | R85: 21.587374 | S85: DOW30 | T85: SI | V85: =Umbrales!$B$9*(K85/1000)^Umbrales!$B$10
A86: ITX.MC | B86: Industria de Diseño Textil, S.A. | C86: Spain | D86: ES | E86: Consumo cíclico | F86: Apparel Retail | G86: MCE | H86: EUR | I86: 172322.31 | J86: =INDEX(FX!$B:$B,MATCH(H86,FX!$A:$A,0)) | K86: =I86*J86 | L86: =IF(U86<>"",U86,IF(K86>=Umbrales!$B$2,"Legendaria",IF(K86>=Umbrales!$B$3,"Épica",IF(K86>=Umbrales!$B$4,"Rara",IF(K86>=Umbrales!$B$5,"Poco común","Común"))))) | M86: 41261.998 | N86: 6408.9999 | O86: =IF(M86="","",M86*J86) | P86: =IF(N86="","",N86*J86) | Q86: 0.012 | R86: 26.85437 | S86: EUROSTOXX50, IBEX35 | T86: SI | V86: =Umbrales!$B$9*(K86/1000)^Umbrales!$B$10
A87: GILD | B87: Gilead Sciences, Inc. | C87: United States | D87: US | E87: Salud | F87: Drug Manufacturers - General | G87: NMS | H87: USD | I87: 190382.72 | J87: =INDEX(FX!$B:$B,MATCH(H87,FX!$A:$A,0)) | K87: =I87*J87 | L87: =IF(U87<>"",U87,IF(K87>=Umbrales!$B$2,"Legendaria",IF(K87>=Umbrales!$B$3,"Épica",IF(K87>=Umbrales!$B$4,"Rara",IF(K87>=Umbrales!$B$5,"Poco común","Común"))))) | M87: 30457 | N87: -3240 | O87: =IF(M87="","",M87*J87) | P87: =IF(N87="","",N87*J87) | Q87: 0.0222 | S87: NASDAQ100 | T87: SI | V87: =Umbrales!$B$9*(K87/1000)^Umbrales!$B$10
A88: DIS | B88: The Walt Disney Company | C88: United States | D88: US | E88: Comunicación | F88: Entertainment | G88: NYQ | H88: USD | I88: 188191.59 | J88: =INDEX(FX!$B:$B,MATCH(H88,FX!$A:$A,0)) | K88: =I88*J88 | L88: =IF(U88<>"",U88,IF(K88>=Umbrales!$B$2,"Legendaria",IF(K88>=Umbrales!$B$3,"Épica",IF(K88>=Umbrales!$B$4,"Rara",IF(K88>=Umbrales!$B$5,"Poco común","Común"))))) | M88: 98860.999 | N88: 8600.0005 | O88: =IF(M88="","",M88*J88) | P88: =IF(N88="","",N88*J88) | Q88: 0.0138 | R88: 22.379877 | S88: DOW30 | T88: SI | V88: =Umbrales!$B$9*(K88/1000)^Umbrales!$B$10
A89: VZ | B89: Verizon Communications Inc. | C89: United States | D89: US | E89: Comunicación | F89: Telecom Services | G89: NYQ | H89: USD | I89: 184555.11 | J89: =INDEX(FX!$B:$B,MATCH(H89,FX!$A:$A,0)) | K89: =I89*J89 | L89: =IF(U89<>"",U89,IF(K89>=Umbrales!$B$2,"Legendaria",IF(K89>=Umbrales!$B$3,"Épica",IF(K89>=Umbrales!$B$4,"Rara",IF(K89>=Umbrales!$B$5,"Poco común","Común"))))) | M89: 138895 | N89: 16172 | O89: =IF(M89="","",M89*J89) | P89: =IF(N89="","",N89*J89) | Q89: 0.065 | R89: 11.331632 | S89: DOW30 | T89: SI | V89: =Umbrales!$B$9*(K89/1000)^Umbrales!$B$10
A90: QCOM | B90: QUALCOMM Incorporated | C90: United States | D90: US | E90: Tecnología | F90: Semiconductors | G90: NMS | H90: USD | I90: 184330.45 | J90: =INDEX(FX!$B:$B,MATCH(H90,FX!$A:$A,0)) | K90: =I90*J90 | L90: =IF(U90<>"",U90,IF(K90>=Umbrales!$B$2,"Legendaria",IF(K90>=Umbrales!$B$3,"Épica",IF(K90>=Umbrales!$B$4,"Rara",IF(K90>=Umbrales!$B$5,"Poco común","Común"))))) | M90: 44068.999 | N90: 9260.0003 | O90: =IF(M90="","",M90*J90) | P90: =IF(N90="","",N90*J90) | Q90: 0.0208 | R90: 20.476868 | S90: NASDAQ100 | T90: SI | V90: =Umbrales!$B$9*(K90/1000)^Umbrales!$B$10
A91: ALV.DE | B91: Allianz SE | C91: Germany | D91: DE | E91: Finanzas | F91: Insurance - Diversified | G91: GER | H91: EUR | I91: 164193.03 | J91: =INDEX(FX!$B:$B,MATCH(H91,FX!$A:$A,0)) | K91: =I91*J91 | L91: =IF(U91<>"",U91,IF(K91>=Umbrales!$B$2,"Legendaria",IF(K91>=Umbrales!$B$3,"Épica",IF(K91>=Umbrales!$B$4,"Rara",IF(K91>=Umbrales!$B$5,"Poco común","Común"))))) | M91: 119421 | N91: 11612 | O91: =IF(M91="","",M91*J91) | P91: =IF(N91="","",N91*J91) | Q91: 0.041 | R91: 13.987076 | S91: DAX40, EUROSTOXX50 | T91: SI | V91: =Umbrales!$B$9*(K91/1000)^Umbrales!$B$10
A92: CBA.AX | B92: Commonwealth Bank of Australia | C92: Australia | D92: AU | E92: Finanzas | F92: Banks - Diversified | G92: ASX | H92: AUD | I92: 261102.13 | J92: =INDEX(FX!$B:$B,MATCH(H92,FX!$A:$A,0)) | K92: =I92*J92 | L92: =IF(U92<>"",U92,IF(K92>=Umbrales!$B$2,"Legendaria",IF(K92>=Umbrales!$B$3,"Épica",IF(K92>=Umbrales!$B$4,"Rara",IF(K92>=Umbrales!$B$5,"Poco común","Común"))))) | M92: 29365 | N92: 10911 | O92: =IF(M92="","",M92*J92) | P92: =IF(N92="","",N92*J92) | Q92: 0.0334 | R92: 23.949385 | S92: ASIA_TOP | T92: SI | V92: =Umbrales!$B$9*(K92/1000)^Umbrales!$B$10
A93: ABT | B93: Abbott Laboratories | C93: United States | D93: US | E93: Salud | F93: Medical Devices | G93: NYQ | H93: USD | I93: 179354.5 | J93: =INDEX(FX!$B:$B,MATCH(H93,FX!$A:$A,0)) | K93: =I93*J93 | L93: =IF(U93<>"",U93,IF(K93>=Umbrales!$B$2,"Legendaria",IF(K93>=Umbrales!$B$3,"Épica",IF(K93>=Umbrales!$B$4,"Rara",IF(K93>=Umbrales!$B$5,"Poco común","Común"))))) | M93: 46585 | N93: 5400.9999 | O93: =IF(M93="","",M93*J93) | P93: =IF(N93="","",N93*J93) | Q93: 0.0246 | R93: 33.109325 | T93: SI | V93: =Umbrales!$B$9*(K93/1000)^Umbrales!$B$10
A94: PEP | B94: PepsiCo, Inc. | C94: United States | D94: US | E94: Consumo básico | F94: Beverages - Non-Alcoholic | G94: NMS | H94: USD | I94: 176161.55 | J94: =INDEX(FX!$B:$B,MATCH(H94,FX!$A:$A,0)) | K94: =I94*J94 | L94: =IF(U94<>"",U94,IF(K94>=Umbrales!$B$2,"Legendaria",IF(K94>=Umbrales!$B$3,"Épica",IF(K94>=Umbrales!$B$4,"Rara",IF(K94>=Umbrales!$B$5,"Poco común","Común"))))) | M94: 98241.004 | N94: 10896 | O94: =IF(M94="","",M94*J94) | P94: =IF(N94="","",N94*J94) | Q94: 0.0465 | R94: 16.018589 | S94: NASDAQ100 | T94: SI | V94: =Umbrales!$B$9*(K94/1000)^Umbrales!$B$10
A95: DE | B95: Deere & Company | C95: United States | D95: US | E95: Industria | F95: Farm & Heavy Construction Machinery | G95: NYQ | H95: USD | I95: 175358.97 | J95: =INDEX(FX!$B:$B,MATCH(H95,FX!$A:$A,0)) | K95: =I95*J95 | L95: =IF(U95<>"",U95,IF(K95>=Umbrales!$B$2,"Legendaria",IF(K95>=Umbrales!$B$3,"Épica",IF(K95>=Umbrales!$B$4,"Rara",IF(K95>=Umbrales!$B$5,"Poco común","Común"))))) | M95: 47927.001 | N95: 4872.9999 | O95: =IF(M95="","",M95*J95) | P95: =IF(N95="","",N95*J95) | Q95: 0.01 | R95: 36.15231 | T95: SI | V95: =Umbrales!$B$9*(K95/1000)^Umbrales!$B$10
A96: 9984.T | B96: SoftBank Group Corp. | C96: Japan | D96: JP | E96: Comunicación | F96: Telecom Services | G96: JPX | H96: JPY | I96: 27651788 | J96: =INDEX(FX!$B:$B,MATCH(H96,FX!$A:$A,0)) | K96: =I96*J96 | L96: =IF(U96<>"",U96,IF(K96>=Umbrales!$B$2,"Legendaria",IF(K96>=Umbrales!$B$3,"Épica",IF(K96>=Umbrales!$B$4,"Rara",IF(K96>=Umbrales!$B$5,"Poco común","Común"))))) | M96: 7997900.2 | N96: 4908440.9 | O96: =IF(M96="","",M96*J96) | P96: =IF(N96="","",N96*J96) | Q96: 0.0021 | R96: 5.647442 | S96: ASIA_TOP | T96: SI | V96: =Umbrales!$B$9*(K96/1000)^Umbrales!$B$10
A97: BLK | B97: BlackRock, Inc. | C97: United States | D97: US | E97: Finanzas | F97: Asset Management | G97: NYQ | H97: USD | I97: 174465.32 | J97: =INDEX(FX!$B:$B,MATCH(H97,FX!$A:$A,0)) | K97: =I97*J97 | L97: =IF(U97<>"",U97,IF(K97>=Umbrales!$B$2,"Legendaria",IF(K97>=Umbrales!$B$3,"Épica",IF(K97>=Umbrales!$B$4,"Rara",IF(K97>=Umbrales!$B$5,"Poco común","Común"))))) | M97: 27299 | N97: 6576 | O97: =IF(M97="","",M97*J97) | P97: =IF(N97="","",N97*J97) | Q97: 0.0215 | R97: 25.517822 | T97: SI | V97: =Umbrales!$B$9*(K97/1000)^Umbrales!$B$10
A98: RELIANCE.NS | B98: Reliance Industries Limited | C98: India | D98: IN | E98: Energía | F98: Oil & Gas Refining & Marketing | G98: NSI | H98: INR | I98: 16437894 | J98: =INDEX(FX!$B:$B,MATCH(H98,FX!$A:$A,0)) | K98: =I98*J98 | L98: =IF(U98<>"",U98,IF(K98>=Umbrales!$B$2,"Legendaria",IF(K98>=Umbrales!$B$3,"Épica",IF(K98>=Umbrales!$B$4,"Rara",IF(K98>=Umbrales!$B$5,"Poco común","Común"))))) | M98: 11296050 | N98: 747269.98 | O98: =IF(M98="","",M98*J98) | P98: =IF(N98="","",N98*J98) | Q98: 0.0051 | R98: 21.997463 | S98: ASIA_TOP | T98: SI | V98: =Umbrales!$B$9*(K98/1000)^Umbrales!$B$10
A99: AIR.PA | B99: Airbus SE | C99: Netherlands | D99: NL | E99: Industria | F99: Aerospace & Defense | G99: PAR | H99: EUR | I99: 152391.65 | J99: =INDEX(FX!$B:$B,MATCH(H99,FX!$A:$A,0)) | K99: =I99*J99 | L99: =IF(U99<>"",U99,IF(K99>=Umbrales!$B$2,"Legendaria",IF(K99>=Umbrales!$B$3,"Épica",IF(K99>=Umbrales!$B$4,"Rara",IF(K99>=Umbrales!$B$5,"Poco común","Común"))))) | M99: 76985.999 | N99: 5938.9998 | O99: =IF(M99="","",M99*J99) | P99: =IF(N99="","",N99*J99) | Q99: 0.0172 | R99: 25.637815 | S99: DAX40, EUROSTOXX50 | T99: SI | V99: =Umbrales!$B$9*(K99/1000)^Umbrales!$B$10
A100: COP | B100: ConocoPhillips | C100: United States | D100: US | E100: Energía | F100: Oil & Gas E&P | G100: NYQ | H100: USD | I100: 170998.37 | J100: =INDEX(FX!$B:$B,MATCH(H100,FX!$A:$A,0)) | K100: =I100*J100 | L100: =IF(U100<>"",U100,IF(K100>=Umbrales!$B$2,"Legendaria",IF(K100>=Umbrales!$B$3,"Épica",IF(K100>=Umbrales!$B$4,"Rara",IF(K100>=Umbrales!$B$5,"Poco común","Común"))))) | M100: 64459.002 | N100: 9253.0002 | O100: =IF(M100="","",M100*J100) | P100: =IF(N100="","",N100*J100) | Q100: 0.0238 | R100: 18.655308 | T100: SI | V100: =Umbrales!$B$9*(K100/1000)^Umbrales!$B$10
...

Sheet FX
A1: Moneda | B1: USD por unidad | C1: Fuente
A2: AUD | B2: 0.69309676 | C2: Yahoo Finance AUDUSD=X, cierre 2026-10-15
A3: CHF | B3: 1.2058798 | C3: Yahoo Finance CHFUSD=X, cierre 2026-10-15
A4: CNY | B4: 0.14945896 | C4: Yahoo Finance CNYUSD=X, cierre 2026-10-15
A5: DKK | B5: 0.15008615 | C5: Yahoo Finance DKKUSD=X, cierre 2026-10-15
A6: EUR | B6: 1.1222085 | C6: Yahoo Finance EURUSD=X, cierre 2026-10-15
A7: GBP | B7: 1.3258907 | C7: Yahoo Finance GBPUSD=X, cierre 2026-10-15
A8: HKD | B8: 0.1274361 | C8: Yahoo Finance HKDUSD=X, cierre 2026-10-15
A9: INR | B9: 0.010527978 | C9: Yahoo Finance INRUSD=X, cierre 2026-10-15
A10: JPY | B10: 0.0063383402 | C10: Yahoo Finance JPYUSD=X, cierre 2026-10-15
A11: KRW | B11: 0.0007440974 | C11: Yahoo Finance KRWUSD=X, cierre 2026-10-15
A12: NOK | B12: 0.10504422 | C12: Yahoo Finance NOKUSD=X, cierre 2026-10-15
A13: SAR | B13: 0.2664535 | C13: Yahoo Finance SARUSD=X, cierre 2026-10-15
... A16: USD | B16: 1 | C16: Yahoo Finance USDUSD=X, cierre 2026-10-15

Sheet Umbrales
A1: Rareza | B1: Cap. mínima (M USD) | C1: Probabilidad gacha | D1: Empresas | E1: % del total
A2: Legendaria | B2: 1200000 | C2: 0.01 | D2: =COUNTIFS(Empresas!$L:$L,A2,Empresas!$T:$T,"SI") | E2: =IF(SUM($D$2:$D$6)=0,0,D2/SUM($D$2:$D$6))
A3: Épica | B3: 350000 | C3: 0.05 | D3: =COUNTIFS(Empresas!$L:$L,A3,Empresas!$T:$T,"SI") | E3: =IF(SUM($D$2:$D$6)=0,0,D3/SUM($D$2:$D$6))
A4: Rara | B4: 150000 | C4: 0.12 | D4: =COUNTIFS(Empresas!$L:$L,A4,Empresas!$T:$T,"SI") | E4: =IF(SUM($D$2:$D$6)=0,0,D4/SUM($D$2:$D$6))
A5: Poco común | B5: 55000 | C5: 0.27 | D5: =COUNTIFS(Empresas!$L:$L,A5,Empresas!$T:$T,"SI") | E5: =IF(SUM($D$2:$D$6)=0,0,D5/SUM($D$2:$D$6))
A6: Común | B6: 0 | C6: 0.55 | D6: =COUNTIFS(Empresas!$L:$L,A6,Empresas!$T:$T,"SI") | E6: =IF(SUM($D$2:$D$6)=0,0,D6/SUM($D$2:$D$6))
A7: Total | C7: =SUM(C2:C6) | D7: =SUM(D2:D6)
A9: Coeficiente ingresos | B9: 0.05
A10: Exponente ingresos | B10: 0.75
A11: ingresos/s = coeficiente × (Cap. USD en miles de millones) ^ exponente
